pyRankMCDA/__init__.py
pyRankMCDA/algorithm/__init__.py
pyRankMCDA/algorithm/src.py
pyRankMCDA-2.1.5.dist-info/LICENSE
pyRankMCDA-2.1.5.dist-info/METADATA
pyRankMCDA-2.1.5.dist-info/WHEEL
pyRankMCDA-2.1.5.dist-info/top_level.txt
pyRankMCDA-2.1.5.dist-info/zip-safe
pyRankMCDA-2.1.5.dist-info/RECORD
