Metadata-Version: 2.1
Name: pyRankMCDA
Version: 2.1.5
Summary: A Rank Aggegation Library for MCDA problems
Home-page: https://github.com/Valdecy/pyRankMCDA
Author: Valdecy Pereira
Author-email: valdecy.pereira@gmail.com
License: GNU
License-File: LICENSE
Requires-Dist: adjustText
Requires-Dist: matplotlib
Requires-Dist: networkx
Requires-Dist: numpy
Requires-Dist: pandas
Requires-Dist: seaborn
Requires-Dist: scipy
Requires-Dist: scikit-learn
